st_default_width.py
st_default_width-0.0.2.dist-info/METADATA
st_default_width-0.0.2.dist-info/WHEEL
st_default_width-0.0.2.dist-info/licenses/LICENSE
st_default_width-0.0.2.dist-info/RECORD
